Nsc616/__init__.py
Nsc616/core.py
Nsc616/exceptions.py
Nsc616/main.py
Nsc616/matchers.py
Nsc616/patterns.py
nsc616-3.1.1.dist-info/METADATA
nsc616-3.1.1.dist-info/WHEEL
nsc616-3.1.1.dist-info/entry_points.txt
nsc616-3.1.1.dist-info/top_level.txt
nsc616-3.1.1.dist-info/RECORD
