Metadata-Version: 2.4
Name: Nsc616
Version: 3.1.1
Summary: Nsc410 增强版表达式处理器
Author: 王子毅
Provides-Extra: dev
Requires-Dist: pytest>=6.0; extra == "dev"
